docker_code_executor/__init__.py
docker_code_executor/_cancellation_token.py
docker_code_executor/_executor.py
docker_code_executor/_func_with_reqs.py
docker_code_executor/_types.py
docker_code_executor/_utils.py
docker_code_executor-0.0.2.dist-info/METADATA
docker_code_executor-0.0.2.dist-info/WHEEL
docker_code_executor-0.0.2.dist-info/RECORD
