Metadata-Version: 2.4
Name: docker-code-executor
Version: 0.0.2
Summary: A code executor that leverages Docker Container
Author: Sachdeva, Kapil
Requires-Python: >=3.11
Requires-Dist: asyncio-atexit>=1.0.1
Requires-Dist: docker>=7.1.0
